sodius2/__init__.py
sodius2/cli_wrapper.py
sodium2-0.1.0.dist-info/METADATA
sodium2-0.1.0.dist-info/WHEEL
sodium2-0.1.0.dist-info/entry_points.txt
sodium2-0.1.0.dist-info/top_level.txt
sodium2-0.1.0.dist-info/RECORD
