Metadata-Version: 2.4
Name: sodium2
Version: 0.1.0
Summary: Copiex process manager
Author-email: Your Name <you@email.com>
License: MIT
Requires-Python: >=3.9
Requires-Dist: psutil
